{
    "partname": "optimization",
    "runtime": 79.81502679700134,
    "results": {
        "CONF1": {
            "xtb_opt": {
                "energy": -386.0055611,
                "grad_norm": 0.000351709977,
                "converged": true,
                "geom": [
                    {
                        "element": "C",
                        "xyz": [
                            -2.5616135535194187,
                            0.6243185153064598,
                            5.9477964254089634e-05
                        ]
                    },
                    {
                        "element": "C",
                        "xyz": [
                            -1.2229419062058913,
                            -0.060685865779612005,
                            5.347079552891272e-05
                        ]
                    },
                    {
                        "element": "C",
                        "xyz": [
                            -1.1510107898076791,
                            -1.4553439235980996,
                            4.8287320998905435e-05
                        ]
                    },
                    {
                        "element": "C",
                        "xyz": [
                            0.08004329661143035,
                            -2.099618842501786,
                            -2.3096254701683762e-05
                        ]
                    },
                    {
                        "element": "C",
                        "xyz": [
                            1.2518856101252087,
                            -1.3559794496984023,
                            -2.8843717386187128e-05
                        ]
                    },
                    {
                        "element": "C",
                        "xyz": [
                            1.1830617741268041,
                            0.03680421550554052,
                            -1.858347965184212e-06
                        ]
                    },
                    {
                        "element": "C",
                        "xyz": [
                            -0.04660366215940605,
                            0.7072366058635333,
                            -1.9956634774715457e-05
                        ]
                    },
                    {
                        "element": "C",
                        "xyz": [
                            -0.10363321936766039,
                            2.209613737835765,
                            -0.00014219845127287826
                        ]
                    },
                    {
                        "element": "O",
                        "xyz": [
                            2.322741707298005,
                            0.8038176525095454,
                            2.6853511329693717e-05
                        ]
                    },
                    {
                        "element": "H",
                        "xyz": [
                            -2.6834936866199124,
                            1.2660704850671773,
                            -0.8801615409681323
                        ]
                    },
                    {
                        "element": "H",
                        "xyz": [
                            -3.3733894149413834,
                            -0.10625670222686512,
                            0.0011247344253946137
                        ]
                    },
                    {
                        "element": "H",
                        "xyz": [
                            -2.682665738688531,
                            1.2677487825978058,
                            0.8791567878833697
                        ]
                    },
                    {
                        "element": "H",
                        "xyz": [
                            -2.0679142785405324,
                            -2.036535639187227,
                            9.250862430006727e-05
                        ]
                    },
                    {
                        "element": "H",
                        "xyz": [
                            0.13043515092309638,
                            -3.1837005715016624,
                            -5.669713623927513e-05
                        ]
                    },
                    {
                        "element": "H",
                        "xyz": [
                            2.2198994966144565,
                            -1.851819606038248,
                            -5.408864912910949e-05
                        ]
                    },
                    {
                        "element": "H",
                        "xyz": [
                            -0.640261131329261,
                            2.582191048619418,
                            -0.8803030504873411
                        ]
                    },
                    {
                        "element": "H",
                        "xyz": [
                            -0.6394471291773739,
                            2.5824070516692577,
                            0.880425362418391
                        ]
                    },
                    {
                        "element": "H",
                        "xyz": [
                            0.8941543160610752,
                            2.6463348889736884,
                            -0.000643272719741593
                        ]
                    },
                    {
                        "element": "H",
                        "xyz": [
                            3.0869280388699645,
                            0.2175936259283125,
                            0.00014848481706946793
                        ]
                    }
                ],
                "cycles": 3,
                "ecyc": [
                    -386.0055005,
                    -386.0055593,
                    -386.0055611
                ],
                "gncyc": [
                    0.018934042117,
                    0.0065279,
                    0.0017034,
                    0.0003325,
                    0.000351709977
                ]
            },
            "xtb_rrho": {
                "energy": 0.123171738494,
                "rmsd": null,
                "gibbs": {
                    "298.15": 0.123171738494
                },
                "enthalpy": {
                    "298.15": null
                },
                "entropy": {
                    "298.15": null
                },
                "symmetry": "c1",
                "symnum": 1,
                "linear": false
            },
            "gtot": -385.882389361506,
            "bmw": 0.40306008765144086
        },
        "CONF2": {
            "xtb_opt": {
                "energy": -386.0054546,
                "grad_norm": 0.00066798112,
                "converged": true,
                "geom": [
                    {
                        "element": "C",
                        "xyz": [
                            -2.585686803540608,
                            0.6022930363630673,
                            0.0010818188832652737
                        ]
                    },
                    {
                        "element": "C",
                        "xyz": [
                            -1.231784575392635,
                            -0.05858550964095281,
                            9.325705516576075e-05
                        ]
                    },
                    {
                        "element": "C",
                        "xyz": [
                            -1.1509485218423718,
                            -1.455066853586913,
                            0.0002677975422482952
                        ]
                    },
                    {
                        "element": "C",
                        "xyz": [
                            0.07915564488621352,
                            -2.0991754155764863,
                            -0.00039339636000951836
                        ]
                    },
                    {
                        "element": "C",
                        "xyz": [
                            1.2525537352347105,
                            -1.3555763680035482,
                            -0.00038182646821649307
                        ]
                    },
                    {
                        "element": "C",
                        "xyz": [
                            1.1737046488027596,
                            0.034255201682263356,
                            -0.00021201205264754166
                        ]
                    },
                    {
                        "element": "C",
                        "xyz": [
                            -0.05595544692244863,
                            0.7062855053763374,
                            -0.0012377934772232156
                        ]
                    },
                    {
                        "element": "C",
                        "xyz": [
                            -0.04386014473239057,
                            2.209371909499403,
                            -0.001613241522186932
                        ]
                    },
                    {
                        "element": "O",
                        "xyz": [
                            2.2976833325481363,
                            0.8232857198274786,
                            0.0015606819939241068
                        ]
                    },
                    {
                        "element": "H",
                        "xyz": [
                            -2.7315738210068554,
                            1.225290648975056,
                            -0.888215381724185
                        ]
                    },
                    {
                        "element": "H",
                        "xyz": [
                            -3.378233485811744,
                            -0.14899224703221328,
                            0.015707238343264575
                        ]
                    },
                    {
                        "element": "H",
                        "xyz": [
                            -2.7198358927794275,
                            1.2478760117443775,
                            0.8757767953777665
                        ]
                    },
                    {
                        "element": "H",
                        "xyz": [
                            -2.0656771269099456,
                            -2.0394606022139254,
                            0.001145552845392098
                        ]
                    },
                    {
                        "element": "H",
                        "xyz": [
                            0.12870575197379192,
                            -3.183350566625025,
                            -0.0003589406710909851
                        ]
                    },
                    {
                        "element": "H",
                        "xyz": [
                            2.222236792140373,
                            -1.8481988255998802,
                            -4.745522464969555e-05
                        ]
                    },
                    {
                        "element": "H",
                        "xyz": [
                            0.4550156556528111,
                            2.5945017574570413,
                            0.8945794305960691
                        ]
                    },
                    {
                        "element": "H",
                        "xyz": [
                            0.5218112203756881,
                            2.592453016744705,
                            -0.8574790032272755
                        ]
                    },
                    {
                        "element": "H",
                        "xyz": [
                            -1.0497157041459173,
                            2.626661387617536,
                            -0.039988280800098606
                        ]
                    },
                    {
                        "element": "H",
                        "xyz": [
                            3.075388819314206,
                            0.25447513308826386,
                            0.0007013097987407675
                        ]
                    }
                ],
                "cycles": 3,
                "ecyc": [
                    -386.0053848,
                    -386.0054497,
                    -386.0054546
                ],
                "gncyc": [
                    0.019492216037,
                    0.0069678,
                    0.0018813,
                    0.0005355,
                    0.00066798112
                ]
            },
            "xtb_rrho": {
                "energy": 0.123174018371,
                "rmsd": null,
                "gibbs": {
                    "298.15": 0.123174018371
                },
                "enthalpy": {
                    "298.15": null
                },
                "entropy": {
                    "298.15": null
                },
                "symmetry": "c1",
                "symnum": 1,
                "linear": false
            },
            "gtot": -385.882280581629,
            "bmw": 0.3591985005509389
        },
        "CONF3": {
            "xtb_opt": {
                "energy": -386.0047143,
                "grad_norm": 0.000357322196,
                "converged": true,
                "geom": [
                    {
                        "element": "C",
                        "xyz": [
                            -2.5951211021270026,
                            0.5802879633500425,
                            -4.97901217549208e-05
                        ]
                    },
                    {
                        "element": "C",
                        "xyz": [
                            -1.2343740164686452,
                            -0.067372508390995,
                            2.2381874140493745e-05
                        ]
                    },
                    {
                        "element": "C",
                        "xyz": [
                            -1.139278595246661,
                            -1.4608482199757928,
                            3.0132851069201538e-05
                        ]
                    },
                    {
                        "element": "C",
                        "xyz": [
                            0.10023670582676038,
                            -2.0917231936182077,
                            6.876743448658008e-05
                        ]
                    },
                    {
                        "element": "C",
                        "xyz": [
                            1.26605104494708,
                            -1.3419621295478423,
                            -4.6171843064751635e-06
                        ]
                    },
                    {
                        "element": "C",
                        "xyz": [
                            1.1764721270297716,
                            0.04712602525648757,
                            -0.00011147254322314285
                        ]
                    },
                    {
                        "element": "C",
                        "xyz": [
                            -0.06171219593325801,
                            0.70686950750452,
                            5.15019393915724e-05
                        ]
                    },
                    {
                        "element": "C",
                        "xyz": [
                            -0.08207127885533437,
                            2.2133847622181655,
                            2.5469987979522227e-06
                        ]
                    },
                    {
                        "element": "O",
                        "xyz": [
                            2.361007101859543,
                            0.7366254977757384,
                            -0.000364493698542229
                        ]
                    },
                    {
                        "element": "H",
                        "xyz": [
                            -2.7447536627957527,
                            1.2116266985557356,
                            0.8830278135330457
                        ]
                    },
                    {
                        "element": "H",
                        "xyz": [
                            -2.7446064670049433,
                            1.2116997980106665,
                            -0.8830995968956095
                        ]
                    },
                    {
                        "element": "H",
                        "xyz": [
                            -3.378744096465913,
                            -0.18032284971044316,
                            -0.00011276751566228776
                        ]
                    },
                    {
                        "element": "H",
                        "xyz": [
                            -2.048175988292858,
                            -2.0542948847949094,
                            1.8151327506090235e-06
                        ]
                    },
                    {
                        "element": "H",
                        "xyz": [
                            0.15822812588444196,
                            -3.175527058572191,
                            9.93663783076012e-05
                        ]
                    },
                    {
                        "element": "H",
                        "xyz": [
                            2.246170725792432,
                            -1.8058918723887842,
                            -6.167093307331258e-05
                        ]
                    },
                    {
                        "element": "H",
                        "xyz": [
                            0.4189399084736353,
                            2.6266616026668417,
                            0.8864596897050114
                        ]
                    },
                    {
                        "element": "H",
                        "xyz": [
                            0.41357026675999725,
                            2.626580740487819,
                            -0.8895211723745642
                        ]
                    },
                    {
                        "element": "H",
                        "xyz": [
                            -1.0985241673039339,
                            2.605233621953679,
                            0.003147276038129117
                        ]
                    },
                    {
                        "element": "H",
                        "xyz": [
                            2.180737942077171,
                            1.6827488075448818,
                            -0.0012525403635336586
                        ]
                    }
                ],
                "cycles": 3,
                "ecyc": [
                    -386.0046552,
                    -386.0047124,
                    -386.0047143
                ],
                "gncyc": [
                    0.019593796745,
                    0.0070297,
                    0.0017971,
                    0.0003327,
                    0.000357322196
                ]
            },
            "xtb_rrho": {
                "energy": 0.123097915559,
                "rmsd": null,
                "gibbs": {
                    "298.15": 0.123097915559
                },
                "enthalpy": {
                    "298.15": null
                },
                "entropy": {
                    "298.15": null
                },
                "symmetry": "c1",
                "symnum": 1,
                "linear": false
            },
            "gtot": -385.881616384441,
            "bmw": 0.17775628132050053
        },
        "CONF4": {
            "xtb_opt": {
                "energy": -386.0035508,
                "grad_norm": 0.000380660422,
                "converged": true,
                "geom": [
                    {
                        "element": "C",
                        "xyz": [
                            -2.5706870122346683,
                            0.6011677493168639,
                            -0.0016327404232782598
                        ]
                    },
                    {
                        "element": "C",
                        "xyz": [
                            -1.223459351140608,
                            -0.06810082378751658,
                            0.00020237080706462105
                        ]
                    },
                    {
                        "element": "C",
                        "xyz": [
                            -1.1384834302200113,
                            -1.4593071214252002,
                            -0.0003564444111851445
                        ]
                    },
                    {
                        "element": "C",
                        "xyz": [
                            0.1006942257306515,
                            -2.091818607551497,
                            0.001334151117156825
                        ]
                    },
                    {
                        "element": "C",
                        "xyz": [
                            1.264221670739602,
                            -1.3418000322618742,
                            0.0015139337446673012
                        ]
                    },
                    {
                        "element": "C",
                        "xyz": [
                            1.1868810258877236,
                            0.050802563462624066,
                            0.00042250258659919115
                        ]
                    },
                    {
                        "element": "C",
                        "xyz": [
                            -0.050758459012001725,
                            0.7112650742660038,
                            0.0023697258834875197
                        ]
                    },
                    {
                        "element": "C",
                        "xyz": [
                            -0.16238485103088451,
                            2.213351813274728,
                            0.002314550793951866
                        ]
                    },
                    {
                        "element": "O",
                        "xyz": [
                            2.3891769106650984,
                            0.7091523154487056,
                            -0.00292564063303118
                        ]
                    },
                    {
                        "element": "H",
                        "xyz": [
                            -2.7100455792172977,
                            1.2313551294441627,
                            0.8845659889569186
                        ]
                    },
                    {
                        "element": "H",
                        "xyz": [
                            -2.6985169902500097,
                            1.2496969361562134,
                            -0.8761712218373517
                        ]
                    },
                    {
                        "element": "H",
                        "xyz": [
                            -3.3714964426007463,
                            -0.14107258221187635,
                            -0.014167431896483808
                        ]
                    },
                    {
                        "element": "H",
                        "xyz": [
                            -2.0501694160292643,
                            -2.0483974083613075,
                            -0.002130291752052003
                        ]
                    },
                    {
                        "element": "H",
                        "xyz": [
                            0.15939355518860976,
                            -3.175483208560444,
                            0.001293852735087545
                        ]
                    },
                    {
                        "element": "H",
                        "xyz": [
                            2.2434397472665624,
                            -1.8072671219852252,
                            0.0010069060337772543
                        ]
                    },
                    {
                        "element": "H",
                        "xyz": [
                            -0.7434764151755564,
                            2.566370112208447,
                            0.8610485939753189
                        ]
                    },
                    {
                        "element": "H",
                        "xyz": [
                            0.7981888626076684,
                            2.7346849564422695,
                            0.048778316107059114
                        ]
                    },
                    {
                        "element": "H",
                        "xyz": [
                            -0.6687969828523781,
                            2.5741990613753885,
                            -0.8999641108134974
                        ]
                    },
                    {
                        "element": "H",
                        "xyz": [
                            2.2344036029127006,
                            1.6590464082150695,
                            -0.013580200451069386
                        ]
                    }
                ],
                "cycles": 4,
                "ecyc": [
                    -386.0034771,
                    -386.0035445,
                    -386.0035499,
                    -386.0035508
                ],
                "gncyc": [
                    0.018769685027,
                    0.0066202,
                    0.0020017,
                    0.0007049,
                    0.0003575,
                    0.000380660422
                ]
            },
            "xtb_rrho": {
                "energy": 0.123099089994,
                "rmsd": null,
                "gibbs": {
                    "298.15": 0.123099089994
                },
                "enthalpy": {
                    "298.15": null
                },
                "entropy": {
                    "298.15": null
                },
                "symmetry": "c1",
                "symnum": 1,
                "linear": false
            },
            "gtot": -385.880451710006,
            "bmw": 0.05177400945090399
        },
        "CONF5": {
            "xtb_opt": {
                "energy": -386.0018153,
                "grad_norm": 0.000410591789,
                "converged": true,
                "geom": [
                    {
                        "element": "C",
                        "xyz": [
                            -2.626926534293073,
                            0.5332631713740514,
                            0.009335735923170262
                        ]
                    },
                    {
                        "element": "C",
                        "xyz": [
                            -1.236630091861796,
                            -0.05441218283612318,
                            -0.0007682230136646314
                        ]
                    },
                    {
                        "element": "C",
                        "xyz": [
                            -1.138294099497501,
                            -1.4514856319247367,
                            -0.002462976874716372
                        ]
                    },
                    {
                        "element": "C",
                        "xyz": [
                            0.09516268465804369,
                            -2.0858223845907364,
                            -0.004006685729634831
                        ]
                    },
                    {
                        "element": "C",
                        "xyz": [
                            1.263780673377014,
                            -1.336975082766946,
                            -0.0009822247033602872
                        ]
                    },
                    {
                        "element": "C",
                        "xyz": [
                            1.1746383935384381,
                            0.04942951903214005,
                            0.0013170676477508132
                        ]
                    },
                    {
                        "element": "C",
                        "xyz": [
                            -0.06442095354885156,
                            0.7191796805563024,
                            -0.003215646232110903
                        ]
                    },
                    {
                        "element": "C",
                        "xyz": [
                            -0.04250330062804249,
                            2.2264326840823543,
                            -0.010214468421779123
                        ]
                    },
                    {
                        "element": "O",
                        "xyz": [
                            2.361799597200378,
                            0.7349429805619915,
                            0.007108248048867739
                        ]
                    },
                    {
                        "element": "H",
                        "xyz": [
                            -2.6488308773987503,
                            1.6218892294330394,
                            -0.00391918756969912
                        ]
                    },
                    {
                        "element": "H",
                        "xyz": [
                            -3.194253338675884,
                            0.18092935877141741,
                            -0.8585014077491594
                        ]
                    },
                    {
                        "element": "H",
                        "xyz": [
                            -3.1688212120245067,
                            0.2052591359512832,
                            0.9028379183497426
                        ]
                    },
                    {
                        "element": "H",
                        "xyz": [
                            -2.0505276982321874,
                            -2.041081467049245,
                            -0.0018687420502028766
                        ]
                    },
                    {
                        "element": "H",
                        "xyz": [
                            0.15049165717152302,
                            -3.1698119896624704,
                            -0.006087573935891339
                        ]
                    },
                    {
                        "element": "H",
                        "xyz": [
                            2.2436137347926706,
                            -1.8014502909377068,
                            0.0005301351971769398
                        ]
                    },
                    {
                        "element": "H",
                        "xyz": [
                            0.4180902685211787,
                            2.6295454650960495,
                            0.9024615619444472
                        ]
                    },
                    {
                        "element": "H",
                        "xyz": [
                            0.5180962393565369,
                            2.6153688889178905,
                            -0.8714686422607175
                        ]
                    },
                    {
                        "element": "H",
                        "xyz": [
                            -1.0388040174962052,
                            2.659184804756017,
                            -0.07311437859377964
                        ]
                    },
                    {
                        "element": "H",
                        "xyz": [
                            2.1869918102602584,
                            1.681763704248472,
                            0.022302663422605333
                        ]
                    }
                ],
                "cycles": 3,
                "ecyc": [
                    -386.0017483,
                    -386.0018119,
                    -386.0018153
                ],
                "gncyc": [
                    0.019342612622,
                    0.0070268,
                    0.0018257,
                    0.0004398,
                    0.000410591789
                ]
            },
            "xtb_rrho": {
                "energy": 0.123102208911,
                "rmsd": null,
                "gibbs": {
                    "298.15": 0.123102208911
                },
                "enthalpy": {
                    "298.15": null
                },
                "entropy": {
                    "298.15": null
                },
                "symmetry": "c1",
                "symnum": 1,
                "linear": false
            },
            "gtot": -385.87871309108897,
            "bmw": 0.008211121026215788
        }
    },
    "settings": {
        "optcycles": 8,
        "maxcyc": 200,
        "threshold": 1.5,
        "hlow": 0.01,
        "gradthr": 0.01,
        "func": "r2scan-3c",
        "basis": "def2-tzvp",
        "prog": "orca",
        "sm": "smd",
        "gfnv": "gfn2",
        "optlevel": "normal",
        "run": true,
        "macrocycles": true,
        "crestcheck": true,
        "template": false,
        "constrain": false,
        "xtb_opt": true
    },
    "nconf_in": 5,
    "nconf_out": 5
}