{
    "partname": "refinement",
    "runtime": 15.633492304004903,
    "results": {
        "CONF1": {
            "sp": {
                "energy": -119.138885353535
            },
            "gtot": -119.138885353535,
            "bmw": 0.9933887824453624
        },
        "CONF2": {
            "sp": {
                "energy": -119.134152769871
            },
            "gtot": -119.134152769871,
            "bmw": 1.0
        }
    },
    "settings": {
        "threshold": 0.95,
        "func": "wb97x-v",
        "basis": "def2-tzvp",
        "prog": "orca",
        "sm": "smd",
        "gfnv": "gfn2",
        "run": true,
        "implicit": false,
        "template": false
    },
    "nconf_in": 2,
    "nconf_out": 1
}